{
  "time_signatures": {
    "4/4": "4/4 time",
    "3/4": "3/4 time",
    "6/8": "6/8 time",
    "12/8": "12/8 time",
    "5/4": "5/4 time",
    "7/8": "7/8 time",
    "9/8": "9/8 time",
    "7/4": "7/4 time",
    "2/4": "2/4 time",
    "2/2": "Cut time",
    "common time": "4/4 time",
    "waltz time": "3/4 time",
    "compound time": "Compound time",
    "3/8": "3/8 time",
    "6/4": "6/4 time",
    "5/8": "5/8 time",
    "11/8": "11/8 time"
  },
  "patterns": {
    "swing": "Swing feel",
    "swing feel": "Swing feel",
    "shuffle": "Shuffle groove",
    "straight": "Straight rhythm",
    "syncopated": "Syncopated groove",
    "syncopation": "Syncopated groove",
    "polyrhythm": "Polyrhythmic",
    "polyrhythmic": "Polyrhythmic",
    "cross-rhythm": "Cross-rhythm",
    "half-time": "Half-time feel",
    "double-time": "Double-time feel",
    "triplet": "Triplet feel",
    "laid-back": "Laid-back groove",
    "laid back": "Laid-back groove",
    "pushed": "Pushed feel",
    "on the beat": "On-the-beat",
    "off-beat": "Off-beat groove",
    "offbeat": "Off-beat groove",
    "four on the floor": "Four-on-the-floor",
    "breakbeat": "Breakbeat pattern",
    "breakbeats": "Breakbeat pattern",
    "two-step": "Two-step groove",
    "two step": "Two-step groove",
    "rubato": "Rubato",
    "straight eighths": "Straight eighths",
    "dotted rhythm": "Dotted rhythm",
    "reggae groove": "Reggae groove",
    "clave": "Clave rhythm",
    "tight groove": "Tight groove",
    "loose groove": "Loose groove",
    "driving rhythm": "Driving rhythm",
    "rolling rhythm": "Rolling rhythm",
    "bouncy": "Bouncy feel",
    "gallop": "Gallop rhythm",
    "blast beat": "Blast beat",
    "blast beats": "Blast beat",
    "dembow": "Dembow rhythm",
    "tresillo": "Tresillo pattern",
    "bossa nova rhythm": "Bossa nova rhythm",
    "montuno": "Montuno pattern",
    "son clave": "Son clave rhythm",
    "rumba clave": "Rumba clave rhythm",
    "second line": "Second line groove",
    "soca beat": "Soca beat",
    "dancehall rhythm": "Dancehall rhythm",
    "reggaeton beat": "Reggaeton beat",
    "afrobeat rhythm": "Afrobeat rhythm",
    "cumbia rhythm": "Cumbia rhythm",
    "march": "March rhythm",
    "marching": "March rhythm",
    "funk groove": "Funk groove",
    "boom bap beat": "Boom bap beat",
    "trap beat": "Trap beat pattern",
    "drill beat": "Drill beat pattern"
  }
}
